feapack/__init__.py
feapack/typing.py
feapack/c/libmkl.py
feapack/gmsh/__init__.py
feapack/gmsh/utility.py
feapack/io/__init__.py
feapack/io/abaqusReader.py
feapack/io/meshReader.py
feapack/model/__init__.py
feapack/model/acceleration.py
feapack/model/bodyLoad.py
feapack/model/boundaryCondition.py
feapack/model/concentratedLoad.py
feapack/model/element.py
feapack/model/elementSet.py
feapack/model/elementTypes.py
feapack/model/exceptions.py
feapack/model/material.py
feapack/model/mdb.py
feapack/model/mesh.py
feapack/model/modelingSpaces.py
feapack/model/node.py
feapack/model/nodeSet.py
feapack/model/odb.py
feapack/model/pressure.py
feapack/model/section.py
feapack/model/sectionTypes.py
feapack/model/surface.py
feapack/model/surfaceSet.py
feapack/model/surfaceTraction.py
feapack/resources/__init__.py
feapack/resources/ico/feapack.ico
feapack/resources/svg/animate-dark.svg
feapack/resources/svg/animate-light.svg
feapack/resources/svg/file-close-dark.svg
feapack/resources/svg/file-close-light.svg
feapack/resources/svg/file-exit-dark.svg
feapack/resources/svg/file-exit-light.svg
feapack/resources/svg/file-open-dark.svg
feapack/resources/svg/file-open-light.svg
feapack/resources/svg/file-print-dark.svg
feapack/resources/svg/file-print-light.svg
feapack/resources/svg/go-to-first-dark.svg
feapack/resources/svg/go-to-first-light.svg
feapack/resources/svg/go-to-last-dark.svg
feapack/resources/svg/go-to-last-light.svg
feapack/resources/svg/go-to-next-dark.svg
feapack/resources/svg/go-to-next-light.svg
feapack/resources/svg/go-to-previous-dark.svg
feapack/resources/svg/go-to-previous-light.svg
feapack/resources/svg/help-about-dark.svg
feapack/resources/svg/help-about-light.svg
feapack/resources/svg/interaction-pan-dark.svg
feapack/resources/svg/interaction-pan-light.svg
feapack/resources/svg/interaction-rotate-dark.svg
feapack/resources/svg/interaction-rotate-light.svg
feapack/resources/svg/interaction-zoom-dark.svg
feapack/resources/svg/interaction-zoom-light.svg
feapack-0.1.1.dist-info/METADATA
feapack-0.1.1.dist-info/WHEEL
feapack-0.1.1.dist-info/licenses/LICENSE
feapack-0.1.1.dist-info/RECORD
